agent/__init__.py
agent/__main__.py
agent/completions.py
agent/config.py
agent/logging.py
agent/rich.py
agent/scaffold.py
agent/tools.py
agent/utils.py
agent/video.py
agent/cli/__init__.py
agent/cli/init.py
agent/cli/main.py
agent/cli/start.py
automators_agent-0.1.8.dist-info/METADATA
automators_agent-0.1.8.dist-info/WHEEL
automators_agent-0.1.8.dist-info/entry_points.txt
automators_agent-0.1.8.dist-info/licenses/LICENSE
automators_agent-0.1.8.dist-info/RECORD
