Metadata-Version: 2.3
Name: automators-agent
Version: 0.1.8
Summary: Automators AI Agent
Requires-Python: >=3.11
Requires-Dist: beautifulsoup4>=4.12.3
Requires-Dist: moviepy>=1.0.3
Requires-Dist: openai>=1.51.2
Requires-Dist: pillow>=11.0.0
Requires-Dist: playwright>=1.47.0
Requires-Dist: pytest-playwright>=0.5.2
Requires-Dist: pytest>=8.3.3
Requires-Dist: python-dotenv>=1.0.1
Requires-Dist: typer>=0.12.5
